sso_client_decorator/__init__.py
sso_client_decorator/flask.py
sso_client_decorator/sso.py
sso_client_decorator/django/__init__.py
sso_client_decorator/django/utils.py
sso_client_decorator-0.0.19.dist-info/METADATA
sso_client_decorator-0.0.19.dist-info/WHEEL
sso_client_decorator-0.0.19.dist-info/top_level.txt
sso_client_decorator-0.0.19.dist-info/RECORD
