Metadata-Version: 2.1
Name: sso-client-decorator
Version: 0.0.19
Summary: client decorator for sso authentication scheme
Home-page: https://github.com/KokocGroup/sso-client-decorator
Author: UNKNOWN
Author-email: UNKNOWN
License: UNKNOWN
Download-URL: https://github.com/KokocGroup/sso-client-decorator/tarball/v0.0.19
Platform: UNKNOWN
Requires-Dist: requests
